LoupeTool/Cal.sh
LoupeTool/ConvertOutput.py
LoupeTool/GetIcityForBLASTHits.py
LoupeTool/Loupe.py
LoupeTool/RemoveFASTAIDRedundency.py
LoupeTool/RunClust.sh
LoupeTool/__init__.py
LoupeTool/entry.py
LoupeTool-0.1.20.dist-info/METADATA
LoupeTool-0.1.20.dist-info/WHEEL
LoupeTool-0.1.20.dist-info/top_level.txt
LoupeTool-0.1.20.dist-info/RECORD
