Metadata-Version: 2.1
Name: LoupeTool
Version: 0.1.20
